oldmemo/__init__.py
oldmemo/etree.py
oldmemo/migrations.py
oldmemo/oldmemo.py
oldmemo/oldmemo_pb2.py
oldmemo/oldmemo_pb2.pyi
oldmemo/py.typed
oldmemo/version.py
oldmemo-2.1.0.dist-info/licenses/LICENSE
oldmemo-2.1.0.dist-info/METADATA
oldmemo-2.1.0.dist-info/WHEEL
oldmemo-2.1.0.dist-info/top_level.txt
oldmemo-2.1.0.dist-info/RECORD
