Metadata-Version: 2.4
Name: Oldmemo
Version: 2.1.0
Summary: Backend implementation of the namespace `eu.siacs.conversations.axolotl` for python-omemo.
Author-email: "Tim Henkes (Syndace)" <me@syndace.dev>
Maintainer-email: "Tim Henkes (Syndace)" <me@syndace.dev>
License-Expression: AGPL-3.0-only
Project-URL: Documentation, https://python-oldmemo.readthedocs.io/
Project-URL: Repository, https://github.com/Syndace/python-oldmemo
Project-URL: Issues, https://github.com/Syndace/python-oldmemo/issues
Project-URL: Changelog, https://github.com/Syndace/python-oldmemo/blob/main/CHANGELOG.md
Classifier: Development Status :: 5 - Production/Stable
Classifier: Programming Language :: Python :: 3
Classifier: Programming Language :: Python :: 3 :: Only
Classifier: Programming Language :: Python :: 3.10
Classifier: Programming Language :: Python :: 3.11
Classifier: Programming Language :: Python :: 3.12
Classifier: Programming Language :: Python :: 3.13
Classifier: Programming Language :: Python :: 3.14
Classifier: Programming Language :: Python :: Implementation :: CPython
Classifier: Programming Language :: Python :: Implementation :: PyPy
Classifier: Intended Audience :: Developers
Classifier: Topic :: Communications :: Chat
Classifier: Topic :: Security :: Cryptography
Requires-Python: >=3.10
License-File: LICENSE
Requires-Dist: OMEMO<3,>=2.0.0
Requires-Dist: DoubleRatchet<2,>=1.2.0
Requires-Dist: X3DH<2,>=1.2.0
Requires-Dist: XEdDSA<2,>=1.0.0
Requires-Dist: cryptography>=3.3.2
Requires-Dist: protobuf>=3.20.3
Requires-Dist: typing-extensions>=4.3.0
Provides-Extra: xml
Requires-Dist: xmlschema>=2.0.2; extra == "xml"
Provides-Extra: docs
Requires-Dist: oldmemo[xml]; extra == "docs"
Requires-Dist: sphinx; extra == "docs"
Requires-Dist: sphinx-rtd-theme; extra == "docs"
Requires-Dist: sphinx-autodoc-typehints; extra == "docs"
Provides-Extra: lint
Requires-Dist: oldmemo[xml]; extra == "lint"
Requires-Dist: mypy; extra == "lint"
Requires-Dist: types-protobuf; extra == "lint"
Requires-Dist: pylint; extra == "lint"
Requires-Dist: flake8; extra == "lint"
Requires-Dist: flake8-pyproject; extra == "lint"
Provides-Extra: dev
Requires-Dist: oldmemo[docs,lint,xml]; extra == "dev"
Requires-Dist: mypy-protobuf; extra == "dev"
Dynamic: license-file
